entropy/__init__.py
entropy/_version.py
entropy/client.py
entropy/errors.py
entropy/hash.py
entropy/ientropy.py
entropy/s3.py
entropy/store.py
entropy/util.py
entropy/web.py
entropy/test/__init__.py
entropy/test/test_client.py
entropy/test/test_errors.py
entropy/test/test_hash.py
entropy/test/test_store.py
entropy/test/test_util.py
entropy/test/util.py
entropy_store-16.1.0.dist-info/DESCRIPTION.rst
entropy_store-16.1.0.dist-info/METADATA
entropy_store-16.1.0.dist-info/RECORD
entropy_store-16.1.0.dist-info/WHEEL
entropy_store-16.1.0.dist-info/metadata.json
entropy_store-16.1.0.dist-info/top_level.txt
xmantissa/plugins/entropyoff.py
