Metadata-Version: 2.0
Name: entropy-store
Version: 16.1.0
Summary: A simple content-addressed immutable object store, with flexible backend support.
Home-page: https://github.com/fusionapp/entropy
Author: Entropy developers
Author-email: UNKNOWN
License: UNKNOWN
Platform: UNKNOWN
Classifier: Development Status :: 4 - Beta
Classifier: Environment :: Web Environment
Classifier: Framework :: Twisted
Classifier: Intended Audience :: Developers
Classifier: License :: OSI Approved :: MIT License
Classifier: Operating System :: OS Independent
Classifier: Programming Language :: Python :: 2.5
Classifier: Programming Language :: Python :: 2.6
Classifier: Programming Language :: Python :: 2.7
Classifier: Topic :: Internet :: WWW/HTTP
Classifier: Topic :: Software Development :: Libraries :: Python Modules
Classifier: Topic :: System :: Archiving
Requires-Dist: Axiom (>=0.7.4)
Requires-Dist: Epsilon (>=0.7.0)
Requires-Dist: Mantissa (>=0.8.0)
Requires-Dist: Nevow (>=0.9.8)
Requires-Dist: Twisted[tls] (>=15.2.1)
Requires-Dist: txAWS (>=0.2)
